redis_file_transfer/__init__.py
redis_file_transfer/__main__.py
redis_file_transfer/client_id.py
redis_file_transfer/fetch.py
redis_file_transfer/filter.py
redis_file_transfer/receive.py
redis_file_transfer/send.py
redis_file_transfer-0.0.5.dist-info/LICENSE
redis_file_transfer-0.0.5.dist-info/METADATA
redis_file_transfer-0.0.5.dist-info/WHEEL
redis_file_transfer-0.0.5.dist-info/entry_points.txt
redis_file_transfer-0.0.5.dist-info/top_level.txt
redis_file_transfer-0.0.5.dist-info/RECORD
